jsonmathpy/README.md
jsonmathpy/__init__.py
jsonmathpy/app.py
jsonmathpy/core/__init__.py
jsonmathpy/core/interpreter.py
jsonmathpy/core/iterator.py
jsonmathpy/core/lexer.py
jsonmathpy/core/nodes.py
jsonmathpy/core/parser.py
jsonmathpy/core/token.py
jsonmathpy/interpreter/__init__.py
jsonmathpy/interpreter/interpreter.py
jsonmathpy/interpreter/service_provider.py
jsonmathpy/parser/__init__.py
jsonmathpy/parser/parser.py
jsonmathpy/parser/service_provider.py
jsonmathpy/shared/__init__.py
jsonmathpy/shared/constants.py
jsonmathpy/shared/interfaces/__init__.py
jsonmathpy/shared/interfaces/interpreter.py
jsonmathpy/shared/interfaces/interpreter_service.py
jsonmathpy/shared/interfaces/iterator.py
jsonmathpy/shared/interfaces/json_math.py
jsonmathpy/shared/interfaces/lexer.py
jsonmathpy/shared/interfaces/node_provider.py
jsonmathpy/shared/interfaces/parser.py
jsonmathpy/shared/interfaces/parser_service.py
jsonmathpy/shared/interfaces/tokens.py
jsonmathpy/shared/models/__init__.py
jsonmathpy/shared/models/basic_nodes.py
jsonmathpy/shared/models/mapper.py
jsonmathpy/shared/models/node_handler.py
jsonmathpy/shared/models/node_keys.py
jsonmathpy/shared/models/object_configuration.py
jsonmathpy/shared/models/token.py
jsonmathpy/tests/tests_e2e.py
jsonmathpy/tests/tests_interpreter.py
jsonmathpy/tests/tests_lexer.py
jsonmathpy/tests/tests_parser.py
jsonmathpy-2.0.7.dist-info/LICENSE
jsonmathpy-2.0.7.dist-info/METADATA
jsonmathpy-2.0.7.dist-info/WHEEL
jsonmathpy-2.0.7.dist-info/RECORD
